docuploader/__init__.py
docuploader/__main__.py
docuploader/credentials.py
docuploader/log.py
docuploader/shell.py
docuploader/tar.py
docuploader/upload.py
docuploader/protos/__init__.py
docuploader/protos/metadata_pb2.py
gcp_docuploader-2019.6.18.dist-info/LICENSE
gcp_docuploader-2019.6.18.dist-info/METADATA
gcp_docuploader-2019.6.18.dist-info/WHEEL
gcp_docuploader-2019.6.18.dist-info/entry_points.txt
gcp_docuploader-2019.6.18.dist-info/top_level.txt
gcp_docuploader-2019.6.18.dist-info/RECORD
