Metadata-Version: 2.1
Name: gcp-docuploader
Version: 2019.6.18
Summary: UNKNOWN
Home-page: UNKNOWN
Author: Google LLC
Author-email: theaflowers@google.com
License: Apache 2.0
Platform: Posix; MacOS X; Windows
Classifier: Development Status :: 3 - Alpha
Classifier: Intended Audience :: Developers
Classifier: License :: OSI Approved :: Apache Software License
Classifier: Programming Language :: Python
Classifier: Programming Language :: Python :: 3.6
Classifier: Operating System :: OS Independent
Classifier: Topic :: Internet
Requires-Dist: click
Requires-Dist: colorlog
Requires-Dist: google-cloud-storage
Requires-Dist: protobuf
